{
	"lastUpdated": "12/05/2020",
	"type": "multiple+interstitial",
	"multiple": [
		{
			"name": "Prank Call Animals",
			"package": "com.quiznbutton.fakecall"
		},
		{
			"name": "Big Brain Test - Puzzles",
			"package": "com.quiznbutton.brainout"
		},
		{
			"name": "Hair Clipper Prank!",
			"package": "com.quiznbutton.hairclipperprank"
		},
		{
			"name": "Yeet Button!",
			"package": "com.quiznbutton.yeet"
		}
	],
	"interstitial": [
		{
			"package": "com.knowledgequizgames.liedetector"
		},
		{
			"package": "com.quiznbutton.hairclipperprank"
		},
		{
			"package": "com.quiznbutton.brainout"
		},
		{
			"package": "com.quiznbutton.yeet"
		}
	]
}